<?xml version="1.0" encoding="utf-8"?>
<!DOCTYPE install PUBLIC "-//Joomla! 3.5//DTD template 1.0//EN" "http://www.joomla.org/xml/dtd/1.6/template-install.dtd">
<extension version="3.5" type="template" client="site">
    <name>Active Cloud</name>
    <creationDate>2017-04-24</creationDate>
    <author>WebGladiolus company</author>
    <authorEmail></authorEmail>
    <authorUrl>http://www.webgladiolus.com/</authorUrl>
    <copyright>© 2017 WebGladiolus company. All Rights Reserved.</copyright>
    <license>GNU General Public License version 2 or later; see LICENSE.txt</license>
    <version>1.0.0</version>
    <description>TPL_WEBGL_ACTIVE_CLOUD_XML_DESCRIPTION</description>

    <files>
        <folder>css</folder>
        <folder>images</folder>
        <folder>js</folder>
        <folder>language</folder>
        <filename>component.php</filename>
        <filename>error.php</filename>
        <filename>favicon.ico</filename>
        <filename>index.php</filename>
        <filename>template_preview.png</filename>
        <filename>template_thumbnail.png</filename>
        <filename>templateDetails.xml</filename>
    </files>

    <positions>
    </positions>

    <languages folder="language">
        <language tag="en-GB">en-GB/en-GB.tpl_whitesquare.ini</language>
        <language tag="en-GB">en-GB/en-GB.tpl_whitesquare.sys.ini</language>

        <language tag="en-GB">he-IL/he-IL.tpl_webgl_active_cloud.ini</language>
        <language tag="en-GB">he-IL/he-IL.tpl_webgl_active_cloud.sys.ini</language>
    </languages>
</extension>